setup.py
vindinium/__init__.py
vindinium/client.py
vindinium.egg-info/PKG-INFO
vindinium.egg-info/SOURCES.txt
vindinium.egg-info/dependency_links.txt
vindinium.egg-info/requires.txt
vindinium.egg-info/top_level.txt
vindinium/ai/__init__.py
vindinium/ai/astar.py
vindinium/ai/minimax/__init__.py
vindinium/ai/minimax/functions.py
vindinium/ai/minimax/minimax.py
vindinium/ai/minimax/simulation.py
vindinium/ai/minimax/state.py
vindinium/bots/__init__.py
vindinium/bots/aggressive_bot.py
vindinium/bots/base_bot.py
vindinium/bots/miner_bot.py
vindinium/bots/minimax_bot.py
vindinium/bots/random_bot.py
vindinium/bots/raw_bot.py
vindinium/models/__init__.py
vindinium/models/game.py
vindinium/models/hero.py
vindinium/models/map.py
vindinium/models/mine.py
vindinium/models/tavern.py
vindinium/utils/__init__.py
vindinium/utils/functions.py
vindinium/utils/heap_queue.py
vindinium/utils/timer.py