Metadata-Version: 1.1
Name: vindinium
Version: 0.1.2
Summary: Python client for vindinium.
Home-page: https://guithub.com/renatopp/vindinium-python/releases
Author: Renato de Pontes Pereira
Author-email: renato.ppontes@gmail.com
License: MIT License
Download-URL: https://guithub.com/renatopp/vindinium-python
Keywords: vindinium game python
Platform: UNKNOWN
Classifier: Development Status :: 5 - Production/Stable
Classifier: Environment :: MacOS X
Classifier: Environment :: Win32 (MS Windows)
Classifier: Environment :: X11 Applications
Classifier: Intended Audience :: Developers
Classifier: License :: OSI Approved :: MIT License
Classifier: Natural Language :: English
Classifier: Operating System :: MacOS :: MacOS X
Classifier: Operating System :: Microsoft :: Windows
Classifier: Operating System :: POSIX :: Linux
Classifier: Programming Language :: Python
Classifier: Topic :: Software Development :: Libraries :: Python Modules
Classifier: Topic :: Scientific/Engineering :: Artificial Intelligence
